Qlearners/ANN.py
Qlearners/Qlearner.py
Qlearners/Simple_ANN.py
Qlearners/__init__.py
Qlearners/epsilon_decay.py
Qlearners/scg.py
Qlearners/version.py
Qlearners/recipes/__init__.py
Qlearners/recipes/cartpole/__init__.py
Qlearners/recipes/cartpole/cartpolebox2d.py
Qlearners/recipes/cartpole/train_adam.py
Qlearners/recipes/cartpole/train_scg.py
Qlearners-0.14.1.dist-info/LICENSE
Qlearners-0.14.1.dist-info/METADATA
Qlearners-0.14.1.dist-info/WHEEL
Qlearners-0.14.1.dist-info/top_level.txt
Qlearners-0.14.1.dist-info/RECORD
