Metadata-Version: 2.1
Name: Qlearners
Version: 0.14.1
Summary: A package for Q learning (and friends)
Home-page: https://github.com/danelliottster/Qlearners
Author: D.L. Elliott
Author-email: danelliottster@gmail.com
Classifier: Intended Audience :: Science/Research
Classifier: Programming Language :: Python :: 3
Classifier: License :: OSI Approved :: MIT License
Classifier: Development Status :: 3 - Alpha
Classifier: License :: OSI Approved :: GNU General Public License v3 (GPLv3)
Requires-Python: >=3.5
License-File: LICENSE
